oxl_ansible_webui/__init__.py
oxl_ansible_webui/__main__.py
oxl_ansible_webui/__script__.py
oxl_ansible_webui/cli.py
oxl_ansible_webui/cli_init.py
oxl_ansible_webui/db.py
oxl_ansible_webui/handle_signals.py
oxl_ansible_webui/main.py
oxl_ansible_webui/manage.py
oxl_ansible_webui/web_serve_static.py
oxl_ansible_webui/webserver.py
oxl_ansible_webui/aw/__init__.py
oxl_ansible_webui/aw/admin.py
oxl_ansible_webui/aw/api.py
oxl_ansible_webui/aw/apps.py
oxl_ansible_webui/aw/base.py
oxl_ansible_webui/aw/dependencies.py
oxl_ansible_webui/aw/main.py
oxl_ansible_webui/aw/models.py
oxl_ansible_webui/aw/settings.py
oxl_ansible_webui/aw/urls.py
oxl_ansible_webui/aw/api_endpoints/__init__.py
oxl_ansible_webui/aw/api_endpoints/alert.py
oxl_ansible_webui/aw/api_endpoints/base.py
oxl_ansible_webui/aw/api_endpoints/credentials.py
oxl_ansible_webui/aw/api_endpoints/credentials_pytest.py
oxl_ansible_webui/aw/api_endpoints/filesystem.py
oxl_ansible_webui/aw/api_endpoints/frontend.py
oxl_ansible_webui/aw/api_endpoints/job.py
oxl_ansible_webui/aw/api_endpoints/job_util.py
oxl_ansible_webui/aw/api_endpoints/key.py
oxl_ansible_webui/aw/api_endpoints/permission.py
oxl_ansible_webui/aw/api_endpoints/repository.py
oxl_ansible_webui/aw/api_endpoints/stats.py
oxl_ansible_webui/aw/api_endpoints/system.py
oxl_ansible_webui/aw/config/__init__.py
oxl_ansible_webui/aw/config/defaults.py
oxl_ansible_webui/aw/config/environment.py
oxl_ansible_webui/aw/config/form_metadata.py
oxl_ansible_webui/aw/config/hardcoded.py
oxl_ansible_webui/aw/config/language.py
oxl_ansible_webui/aw/config/load_file.py
oxl_ansible_webui/aw/config/main.py
oxl_ansible_webui/aw/config/languages/de.py
oxl_ansible_webui/aw/config/languages/en.py
oxl_ansible_webui/aw/config/languages/es.py
oxl_ansible_webui/aw/execute/__init__.py
oxl_ansible_webui/aw/execute/alert.py
oxl_ansible_webui/aw/execute/play.py
oxl_ansible_webui/aw/execute/play_credentials.py
oxl_ansible_webui/aw/execute/play_util.py
oxl_ansible_webui/aw/execute/queue.py
oxl_ansible_webui-0.9.0.dist-info/licenses/LICENSE
oxl_ansible_webui-0.9.0.dist-info/METADATA
oxl_ansible_webui-0.9.0.dist-info/WHEEL
oxl_ansible_webui-0.9.0.dist-info/entry_points.txt
oxl_ansible_webui-0.9.0.dist-info/top_level.txt
oxl_ansible_webui-0.9.0.dist-info/RECORD
