Metadata-Version: 2.4
Name: oxl-ansible-webui
Version: 0.9.0
Summary: Basic WebUI for using Ansible
Author-email: OXL IT-Services <contact@OXL.at>
Project-URL: Homepage, https://github.com/O-X-L/ansible-webui
Project-URL: Documentation, https://ansible-webui.OXL.app/
Project-URL: Repository, https://github.com/O-X-L/ansible-webui.git
Project-URL: Issues, https://github.com/O-X-L/ansible-webui/issues
Keywords: ansible,webui,automation,iac
Classifier: Programming Language :: Python :: 3
Classifier: License :: OSI Approved :: GNU General Public License v3 (GPLv3)
Classifier: Framework :: Django
Requires-Python: >=3.11
License-File: LICENSE
Requires-Dist: gunicorn
Requires-Dist: Django==5.1.*
Requires-Dist: pytz
Requires-Dist: pycryptodome
Requires-Dist: djangorestframework==3.*
Requires-Dist: djangorestframework-api-key==2.*
Requires-Dist: drf-spectacular
Requires-Dist: crontab
Requires-Dist: ansible-core
Requires-Dist: ansibleguy-runner==2.4.0.post5
Requires-Dist: PyYAML
Requires-Dist: premailer
Requires-Dist: oxl_utils
Provides-Extra: mysql
Requires-Dist: mysqlclient; extra == "mysql"
Provides-Extra: psql
Requires-Dist: psycopg[binary,pool]; extra == "psql"
Provides-Extra: saml
Requires-Dist: grafana-django-saml2-auth; extra == "saml"
Provides-Extra: ara
Requires-Dist: ara; extra == "ara"
Dynamic: license-file
